openhivenpy/__init__.py
openhivenpy/base_types.py
openhivenpy/env_config.py
openhivenpy/exceptions.py
openhivenpy/openhivenpy.env
openhivenpy/utils.py
openhivenpy/__pycache__/__init__.cpython-37.pyc
openhivenpy/__pycache__/__init__.cpython-39.pyc
openhivenpy/__pycache__/base_types.cpython-37.pyc
openhivenpy/__pycache__/base_types.cpython-39.pyc
openhivenpy/__pycache__/env_config.cpython-37.pyc
openhivenpy/__pycache__/env_config.cpython-39.pyc
openhivenpy/__pycache__/event_parsers.cpython-39.pyc
openhivenpy/__pycache__/events.cpython-39.pyc
openhivenpy/__pycache__/exceptions.cpython-37.pyc
openhivenpy/__pycache__/exceptions.cpython-39.pyc
openhivenpy/__pycache__/utils.cpython-37.pyc
openhivenpy/__pycache__/utils.cpython-39.pyc
openhivenpy/client/__init__.py
openhivenpy/client/botclient.py
openhivenpy/client/cache.py
openhivenpy/client/hivenclient.py
openhivenpy/client/userclient.py
openhivenpy/client/__pycache__/__init__.cpython-37.pyc
openhivenpy/client/__pycache__/__init__.cpython-39.pyc
openhivenpy/client/__pycache__/botclient.cpython-37.pyc
openhivenpy/client/__pycache__/botclient.cpython-39.pyc
openhivenpy/client/__pycache__/cache.cpython-37.pyc
openhivenpy/client/__pycache__/cache.cpython-39.pyc
openhivenpy/client/__pycache__/hivenclient.cpython-37.pyc
openhivenpy/client/__pycache__/hivenclient.cpython-39.pyc
openhivenpy/client/__pycache__/userclient.cpython-37.pyc
openhivenpy/client/__pycache__/userclient.cpython-39.pyc
openhivenpy/events/__init__.py
openhivenpy/events/event_parsers.py
openhivenpy/events/__pycache__/__init__.cpython-37.pyc
openhivenpy/events/__pycache__/__init__.cpython-39.pyc
openhivenpy/events/__pycache__/event_parsers.cpython-37.pyc
openhivenpy/events/__pycache__/event_parsers.cpython-39.pyc
openhivenpy/gateway/__init__.py
openhivenpy/gateway/http.py
openhivenpy/gateway/messagebroker.py
openhivenpy/gateway/websocket.py
openhivenpy/gateway/__pycache__/__init__.cpython-37.pyc
openhivenpy/gateway/__pycache__/__init__.cpython-39.pyc
openhivenpy-0.2.post1.dist-info/LICENSE
openhivenpy-0.2.post1.dist-info/METADATA
openhivenpy-0.2.post1.dist-info/WHEEL
openhivenpy-0.2.post1.dist-info/top_level.txt
openhivenpy-0.2.post1.dist-info/RECORD
