Metadata-Version: 2.1
Name: openhivenpy
Version: 0.2.post1
Summary: The OpenSource Python API Wrapper and Bot-Framework for Hiven
Home-page: https://github.com/Luna-Klatzer/openhiven.py
Author: Luna Klatzer
Author-email: luna.klatzer@gmail.com
License: MIT
Project-URL: Docs, https://luna-klatzer.github.io/openhiven.py/latest/
Project-URL: Hiven API Docs, https://luna-klatzer.github.io/openhiven.py/latest/api_reference/hiven_restapi.html
Project-URL: Issue-Page, https://github.com/Luna-Klatzer/openhiven.py/issues/
Project-URL: Changelog, https://luna-klatzer.github.io/openhiven.py/latest/changelog.html
Platform: UNKNOWN
Classifier: Programming Language :: Python :: 3
Classifier: Programming Language :: Python :: 3.7
Classifier: Programming Language :: Python :: 3.8
Classifier: Programming Language :: Python :: 3.9
Classifier: License :: OSI Approved :: MIT License
Classifier: Development Status :: 2 - Pre-Alpha
Classifier: Intended Audience :: Developers
Classifier: Operating System :: POSIX
Classifier: Operating System :: MacOS :: MacOS X
Classifier: Operating System :: Microsoft :: Windows
Requires-Python: >=3.7
License-File: LICENSE
Requires-Dist: aiohttp[speedups] (>=3.6)
Requires-Dist: python-dotenv (>=0.15.0)
Requires-Dist: yarl
Requires-Dist: fastjsonschema (>=2.0)
